README.md
pyproject.toml
setup.py
nhentaio/__init__.py
nhentaio/asset.py
nhentaio/better_enums.py
nhentaio/client.py
nhentaio/enums.py
nhentaio/errors.py
nhentaio/gallery.py
nhentaio/http.py
nhentaio/iterators.py
nhentaio/query.py
nhentaio/taglike.py
nhentaio.egg-info/PKG-INFO
nhentaio.egg-info/SOURCES.txt
nhentaio.egg-info/dependency_links.txt
nhentaio.egg-info/requires.txt
nhentaio.egg-info/top_level.txt