Metadata-Version: 2.1
Name: nhentaio
Version: 0.2.0
Summary: An asynchronous, read-only nhentai API wrapper for the damned, depraved, and disillusioned.
Home-page: https://github.com/kaylynn234/nhentaio/
Author: Kaylynn
License: MIT
Project-URL: Documentation, https://nhentaio.readthedocs.io/en/latest/
Project-URL: Issue tracker, https://github.com/kaylynn234/nhentaio/issues
Platform: UNKNOWN
Classifier: License :: OSI Approved :: MIT License
Classifier: Intended Audience :: Developers
Classifier: Natural Language :: English
Classifier: Operating System :: OS Independent
Classifier: Programming Language :: Python :: 3.7
Classifier: Programming Language :: Python :: 3.8
Classifier: Programming Language :: Python :: 3.9
Classifier: Topic :: Internet
Requires-Python: >=3.7.0
